LICENSE
MANIFEST.in
README.md
requirements.txt
setup.py
seek/__init__.py
seek/search.py
seek/seek.py
seek.egg-info/PKG-INFO
seek.egg-info/SOURCES.txt
seek.egg-info/dependency_links.txt
seek.egg-info/entry_points.txt
seek.egg-info/requires.txt
seek.egg-info/top_level.txt