Metadata-Version: 1.1
Name: seek
Version: 0.2.3
Summary: Terminal search and speed reader.
Home-page: https://github.com/Miserlou/Seek
Author: Rich Jones
Author-email: rich@openwatch.net
License: MIT License
Platform: UNKNOWN
Classifier: Environment :: Console
Classifier: License :: OSI Approved :: Apache Software License
Classifier: Operating System :: OS Independent
Classifier: Programming Language :: Python
Classifier: Programming Language :: Python :: 2.6
Classifier: Programming Language :: Python :: 2.7
Classifier: Topic :: Internet :: WWW/HTTP
Classifier: Topic :: Internet :: WWW/HTTP :: Dynamic Content
